pcts/__init__.py
pcts/_modidx.py
pcts/core.py
pcts-0.0.3.dist-info/LICENSE
pcts-0.0.3.dist-info/METADATA
pcts-0.0.3.dist-info/WHEEL
pcts-0.0.3.dist-info/entry_points.txt
pcts-0.0.3.dist-info/top_level.txt
pcts-0.0.3.dist-info/RECORD
